{"nodes": [{"id": "achyut_resume_optimized_orig", "label": "Achyut Niroula Resume (Original/Optimized Version)", "file_type": "document", "source_file": "backend/uploads/ResumeOrig.pdf", "source_location": null, "source_url": null, "captured_at": null, "author": "Achyut Niroula", "contributor": null}, {"id": "achyut_proj_cloud_chat", "label": "Project: Cloud Chat Distributed Messaging System", "file_type": "document", "source_file": "backend/uploads/ResumeOrig.pdf", "source_location": null, "source_url": null, "captured_at": null, "author": "Achyut Niroula", "contributor": null}, {"id": "achyut_proj_multimodal_video", "label": "Project: Multimodal Video Understanding Platform", "file_type": "document", "source_file": "backend/uploads/ResumeOrig.pdf", "source_location": null, "source_url": null, "captured_at": null, "author": "Achyut Niroula", "contributor": null}], "edges": [{"source": "person_achyut_niroula", "target": "achyut_resume_optimized_orig", "relation": "references", "confidence": "EXTRACTED", "confidence_score": 1.0, "source_file": "backend/uploads/ResumeOrig.pdf", "source_location": null, "weight": 1.0}, {"source": "achyut_resume_optimized_orig", "target": "achyut_proj_multimodal_video", "relation": "references", "confidence": "EXTRACTED", "confidence_score": 1.0, "source_file": "backend/uploads/ResumeOrig.pdf", "source_location": null, "weight": 1.0}, {"source": "achyut_resume_optimized_orig", "target": "achyut_proj_cloud_chat", "relation": "references", "confidence": "EXTRACTED", "confidence_score": 1.0, "source_file": "backend/uploads/ResumeOrig.pdf", "source_location": null, "weight": 1.0}, {"source": "achyut_proj_multimodal_video", "target": "achyut_proj_ai_video", "relation": "semantically_similar_to", "confidence": "INFERRED", "confidence_score": 0.88, "source_file": "backend/uploads/ResumeOrig.pdf", "source_location": null, "weight": 0.88}], "hyperedges": []}